{
  "id": "dim_hcdc_sample_data--uig",
  "name": "DIM_HCDC_SAMPLE_DATA",
  "type": "DIMENSION",
  "inputDatasets": [
    {
      "datasetId": "hcdc_sample_data-u2zy",
      "name": "HCDC_SAMPLE_DATA",
      "projectId": "{{ref(project.current.projectId)}}",
      "taskId": "transform-u2zw"
    }
  ],
  "datasetAttributes": {
    "materialized": "ON",
    "hasHistory": "INHERIT",
    "hasLiveViews": "INHERIT",
    "hasChanges": "INHERIT",
    "hasStandardViewsWithHeaders": "ON",
    "watermarkIncrementalSettings": "INHERIT"
  },
  "tableDef": {
    "name": "DIM_HCDC_SAMPLE_DATA",
    "columns": [
      {
        "name": "RESPONSE_COUNT",
        "ordinal": 1,
        "nullable": true,
        "primaryKeyOrdinal": 1,
        "datatype": {
          "type": "INT8",
          "length": 0,
          "precision": 0,
          "scale": 0,
          "originalTypeFull": "BIGINT"
        },
        "id": "response count",
        "flags": "NONE",
        "properties": {
          "documentMetadata": false
        }
      },
      {
        "name": "PROGRAM_NAME",
        "ordinal": 2,
        "nullable": true,
        "primaryKeyOrdinal": 0,
        "datatype": {
          "type": "STRING",
          "length": 8,
          "precision": 0,
          "scale": 0,
          "originalTypeFull": "VARCHAR(8)"
        },
        "id": "program name",
        "flags": "NONE",
        "properties": {
          "documentMetadata": false
        }
      },
      {
        "name": "ELEMENT_AGENCY_SERVICE",
        "ordinal": 3,
        "nullable": true,
        "primaryKeyOrdinal": 0,
        "datatype": {
          "type": "STRING",
          "length": 8,
          "precision": 0,
          "scale": 0,
          "originalTypeFull": "VARCHAR(8)"
        },
        "id": "element_agency_service",
        "flags": "NONE",
        "properties": {
          "documentMetadata": false
        }
      },
      {
        "name": "EXPENDITURE_CENTER",
        "ordinal": 4,
        "nullable": true,
        "primaryKeyOrdinal": 0,
        "datatype": {
          "type": "STRING",
          "length": 32,
          "precision": 0,
          "scale": 0,
          "originalTypeFull": "VARCHAR(32)"
        },
        "id": "expenditure center",
        "flags": "NONE",
        "properties": {
          "documentMetadata": false
        }
      },
      {
        "name": "BUDGET_CATEGORY",
        "ordinal": 5,
        "nullable": true,
        "primaryKeyOrdinal": 0,
        "datatype": {
          "type": "STRING",
          "length": 10,
          "precision": 0,
          "scale": 0,
          "originalTypeFull": "VARCHAR(10)"
        },
        "id": "budget category",
        "flags": "NONE",
        "properties": {
          "documentMetadata": false
        }
      },
      {
        "name": "PERSONNEL_TYPE",
        "ordinal": 6,
        "nullable": true,
        "primaryKeyOrdinal": 0,
        "datatype": {
          "type": "STRING",
          "length": 8,
          "precision": 0,
          "scale": 0,
          "originalTypeFull": "VARCHAR(8)"
        },
        "id": "personnel type",
        "flags": "NONE",
        "properties": {
          "documentMetadata": false
        }
      },
      {
        "name": "EMPLOYEE_TYPE",
        "ordinal": 7,
        "nullable": true,
        "primaryKeyOrdinal": 0,
        "datatype": {
          "type": "STRING",
          "length": 32,
          "precision": 0,
          "scale": 0,
          "originalTypeFull": "VARCHAR(32)"
        },
        "id": "employee type",
        "flags": "NONE",
        "properties": {
          "documentMetadata": false
        }
      },
      {
        "name": "EMPLOYEE_ID_NUMBER_NO_SSNS",
        "ordinal": 8,
        "nullable": true,
        "primaryKeyOrdinal": 0,
        "datatype": {
          "type": "STRING",
          "length": 1,
          "precision": 0,
          "scale": 0,
          "originalTypeFull": "VARCHAR(1)"
        },
        "id": "employee_id_number_no_ssns",
        "flags": "NONE",
        "properties": {
          "documentMetadata": false
        }
      },
      {
        "name": "GRADE_RANK",
        "ordinal": 9,
        "nullable": true,
        "primaryKeyOrdinal": 0,
        "datatype": {
          "type": "STRING",
          "length": 8,
          "precision": 0,
          "scale": 0,
          "originalTypeFull": "VARCHAR(8)"
        },
        "id": "grade/rank",
        "flags": "NONE",
        "properties": {
          "documentMetadata": false
        }
      },
      {
        "name": "BIRTH_YEAR_YYYY",
        "ordinal": 10,
        "nullable": true,
        "primaryKeyOrdinal": 0,
        "datatype": {
          "type": "INT8",
          "length": 0,
          "precision": 0,
          "scale": 0,
          "originalTypeFull": "BIGINT"
        },
        "id": "birth_year_yyyy",
        "flags": "NONE",
        "properties": {
          "documentMetadata": false
        }
      },
      {
        "name": "TOTAL_YEARS_OF_FEDERAL_SERVICE",
        "ordinal": 11,
        "nullable": true,
        "primaryKeyOrdinal": 0,
        "datatype": {
          "type": "STRING",
          "length": 4,
          "precision": 0,
          "scale": 0,
          "originalTypeFull": "VARCHAR(4)"
        },
        "id": "total years of federal service",
        "flags": "NONE",
        "properties": {
          "documentMetadata": false
        }
      },
      {
        "name": "SERVICE_COMPUTATION_DATE_MM_DD_YYYY",
        "ordinal": 12,
        "nullable": true,
        "primaryKeyOrdinal": 0,
        "datatype": {
          "type": "STRING",
          "length": 1,
          "precision": 0,
          "scale": 0,
          "originalTypeFull": "VARCHAR(1)"
        },
        "id": "service_computation_date_mm_dd_yyyy",
        "flags": "NONE",
        "properties": {
          "documentMetadata": false
        }
      },
      {
        "name": "FEDERAL_RETIREMENT_SYSTEM",
        "ordinal": 13,
        "nullable": true,
        "primaryKeyOrdinal": 0,
        "datatype": {
          "type": "STRING",
          "length": 1,
          "precision": 0,
          "scale": 0,
          "originalTypeFull": "VARCHAR(1)"
        },
        "id": "federal retirement system",
        "flags": "NONE",
        "properties": {
          "documentMetadata": false
        }
      },
      {
        "name": "RETIREMENT_ELIGIBILITY_DATE_MM_DD_YYYY",
        "ordinal": 14,
        "nullable": true,
        "primaryKeyOrdinal": 0,
        "datatype": {
          "type": "INT8",
          "length": 0,
          "precision": 0,
          "scale": 0,
          "originalTypeFull": "BIGINT"
        },
        "id": "retirement_eligibility_date_mm_dd_yyyy",
        "flags": "NONE",
        "properties": {
          "documentMetadata": false
        }
      },
      {
        "name": "YEAR_OF_HIRE_AT_AGENCY",
        "ordinal": 15,
        "nullable": true,
        "primaryKeyOrdinal": 0,
        "datatype": {
          "type": "INT8",
          "length": 0,
          "precision": 0,
          "scale": 0,
          "originalTypeFull": "BIGINT"
        },
        "id": "year of hire at agency",
        "flags": "NONE",
        "properties": {
          "documentMetadata": false
        }
      },
      {
        "name": "WORK_ROLE_OCCUPATION_CAREER_SERVICE",
        "ordinal": 16,
        "nullable": true,
        "primaryKeyOrdinal": 0,
        "datatype": {
          "type": "STRING",
          "length": 1,
          "precision": 0,
          "scale": 0,
          "originalTypeFull": "VARCHAR(1)"
        },
        "id": "work_role_occupation_career_service",
        "flags": "NONE",
        "properties": {
          "documentMetadata": false
        }
      },
      {
        "name": "REIMBURSABLE",
        "ordinal": 17,
        "nullable": true,
        "primaryKeyOrdinal": 0,
        "datatype": {
          "type": "STRING",
          "length": 1,
          "precision": 0,
          "scale": 0,
          "originalTypeFull": "VARCHAR(1)"
        },
        "id": "reimbursable",
        "flags": "NONE",
        "properties": {
          "documentMetadata": false
        }
      },
      {
        "name": "HOME_AGENCY",
        "ordinal": 18,
        "nullable": true,
        "primaryKeyOrdinal": 0,
        "datatype": {
          "type": "STRING",
          "length": 1,
          "precision": 0,
          "scale": 0,
          "originalTypeFull": "VARCHAR(1)"
        },
        "id": "home agency",
        "flags": "NONE",
        "properties": {
          "documentMetadata": false
        }
      },
      {
        "name": "HOST_AGENCY",
        "ordinal": 19,
        "nullable": true,
        "primaryKeyOrdinal": 0,
        "datatype": {
          "type": "STRING",
          "length": 1,
          "precision": 0,
          "scale": 0,
          "originalTypeFull": "VARCHAR(1)"
        },
        "id": "host agency",
        "flags": "NONE",
        "properties": {
          "documentMetadata": false
        }
      },
      {
        "name": "COMMENTS",
        "ordinal": 20,
        "nullable": true,
        "primaryKeyOrdinal": 0,
        "datatype": {
          "type": "STRING",
          "length": 1,
          "precision": 0,
          "scale": 0,
          "originalTypeFull": "VARCHAR(1)"
        },
        "id": "comments",
        "flags": "NONE",
        "properties": {
          "documentMetadata": false
        }
      },
      {
        "name": "ELEMENT_AGENCY_OR_SERVICE",
        "ordinal": 21,
        "nullable": true,
        "primaryKeyOrdinal": 0,
        "datatype": {
          "type": "STRING",
          "length": 8,
          "precision": 0,
          "scale": 0,
          "originalTypeFull": "VARCHAR(8)"
        },
        "id": "element_agency_or_service",
        "flags": "NONE",
        "properties": {
          "documentMetadata": false
        }
      }
    ],
    "entityId": "",
    "secureQri": "",
    "fullLoadOnly": false
  },
  "dimensionDatasetSettings": {
    "type": "TYPE2",
    "rootDataEntityId": {
      "type": "NONE",
      "entityId": "hcdc_sample_data-u2zy",
      "name": "HCDC_SAMPLE_DATA",
      "projectId": "{{ref(project.current.projectId)}}",
      "dataAppId": "transform-u2zw"
    },
    "mapping": {
      "columns": [
        {
          "columnName": "RESPONSE_COUNT",
          "type": "ROOT_PK",
          "expression": {
            "expressionStatement": "${RESPONSE_COUNT}",
            "alias": [
              {
                "name": "RESPONSE_COUNT",
                "value": "RESPONSE_COUNT"
              }
            ]
          }
        },
        {
          "columnName": "PROGRAM_NAME",
          "type": "NONE",
          "expression": {
            "expressionStatement": "${PROGRAM_NAME}",
            "alias": [
              {
                "name": "PROGRAM_NAME",
                "value": "PROGRAM_NAME"
              }
            ]
          }
        },
        {
          "columnName": "ELEMENT_AGENCY_SERVICE",
          "type": "NONE",
          "expression": {
            "expressionStatement": "${ELEMENT_AGENCY_SERVICE}",
            "alias": [
              {
                "name": "ELEMENT_AGENCY_SERVICE",
                "value": "ELEMENT_AGENCY_SERVICE"
              }
            ]
          }
        },
        {
          "columnName": "EXPENDITURE_CENTER",
          "type": "NONE",
          "expression": {
            "expressionStatement": "${EXPENDITURE_CENTER}",
            "alias": [
              {
                "name": "EXPENDITURE_CENTER",
                "value": "EXPENDITURE_CENTER"
              }
            ]
          }
        },
        {
          "columnName": "BUDGET_CATEGORY",
          "type": "NONE",
          "expression": {
            "expressionStatement": "${BUDGET_CATEGORY}",
            "alias": [
              {
                "name": "BUDGET_CATEGORY",
                "value": "BUDGET_CATEGORY"
              }
            ]
          }
        },
        {
          "columnName": "PERSONNEL_TYPE",
          "type": "NONE",
          "expression": {
            "expressionStatement": "${PERSONNEL_TYPE}",
            "alias": [
              {
                "name": "PERSONNEL_TYPE",
                "value": "PERSONNEL_TYPE"
              }
            ]
          }
        },
        {
          "columnName": "EMPLOYEE_TYPE",
          "type": "NONE",
          "expression": {
            "expressionStatement": "${EMPLOYEE_TYPE}",
            "alias": [
              {
                "name": "EMPLOYEE_TYPE",
                "value": "EMPLOYEE_TYPE"
              }
            ]
          }
        },
        {
          "columnName": "EMPLOYEE_ID_NUMBER_NO_SSNS",
          "type": "NONE",
          "expression": {
            "expressionStatement": "${EMPLOYEE_ID_NUMBER_NO_SSNS}",
            "alias": [
              {
                "name": "EMPLOYEE_ID_NUMBER_NO_SSNS",
                "value": "EMPLOYEE_ID_NUMBER_NO_SSNS"
              }
            ]
          }
        },
        {
          "columnName": "GRADE_RANK",
          "type": "NONE",
          "expression": {
            "expressionStatement": "${GRADE_RANK}",
            "alias": [
              {
                "name": "GRADE_RANK",
                "value": "GRADE_RANK"
              }
            ]
          }
        },
        {
          "columnName": "BIRTH_YEAR_YYYY",
          "type": "NONE",
          "expression": {
            "expressionStatement": "${BIRTH_YEAR_YYYY}",
            "alias": [
              {
                "name": "BIRTH_YEAR_YYYY",
                "value": "BIRTH_YEAR_YYYY"
              }
            ]
          }
        },
        {
          "columnName": "TOTAL_YEARS_OF_FEDERAL_SERVICE",
          "type": "NONE",
          "expression": {
            "expressionStatement": "${TOTAL_YEARS_OF_FEDERAL_SERVICE}",
            "alias": [
              {
                "name": "TOTAL_YEARS_OF_FEDERAL_SERVICE",
                "value": "TOTAL_YEARS_OF_FEDERAL_SERVICE"
              }
            ]
          }
        },
        {
          "columnName": "SERVICE_COMPUTATION_DATE_MM_DD_YYYY",
          "type": "NONE",
          "expression": {
            "expressionStatement": "${SERVICE_COMPUTATION_DATE_MM_DD_YYYY}",
            "alias": [
              {
                "name": "SERVICE_COMPUTATION_DATE_MM_DD_YYYY",
                "value": "SERVICE_COMPUTATION_DATE_MM_DD_YYYY"
              }
            ]
          }
        },
        {
          "columnName": "FEDERAL_RETIREMENT_SYSTEM",
          "type": "NONE",
          "expression": {
            "expressionStatement": "${FEDERAL_RETIREMENT_SYSTEM}",
            "alias": [
              {
                "name": "FEDERAL_RETIREMENT_SYSTEM",
                "value": "FEDERAL_RETIREMENT_SYSTEM"
              }
            ]
          }
        },
        {
          "columnName": "RETIREMENT_ELIGIBILITY_DATE_MM_DD_YYYY",
          "type": "NONE",
          "expression": {
            "expressionStatement": "${RETIREMENT_ELIGIBILITY_DATE_MM_DD_YYYY}",
            "alias": [
              {
                "name": "RETIREMENT_ELIGIBILITY_DATE_MM_DD_YYYY",
                "value": "RETIREMENT_ELIGIBILITY_DATE_MM_DD_YYYY"
              }
            ]
          }
        },
        {
          "columnName": "YEAR_OF_HIRE_AT_AGENCY",
          "type": "NONE",
          "expression": {
            "expressionStatement": "${YEAR_OF_HIRE_AT_AGENCY}",
            "alias": [
              {
                "name": "YEAR_OF_HIRE_AT_AGENCY",
                "value": "YEAR_OF_HIRE_AT_AGENCY"
              }
            ]
          }
        },
        {
          "columnName": "WORK_ROLE_OCCUPATION_CAREER_SERVICE",
          "type": "NONE",
          "expression": {
            "expressionStatement": "${WORK_ROLE_OCCUPATION_CAREER_SERVICE}",
            "alias": [
              {
                "name": "WORK_ROLE_OCCUPATION_CAREER_SERVICE",
                "value": "WORK_ROLE_OCCUPATION_CAREER_SERVICE"
              }
            ]
          }
        },
        {
          "columnName": "REIMBURSABLE",
          "type": "NONE",
          "expression": {
            "expressionStatement": "${REIMBURSABLE}",
            "alias": [
              {
                "name": "REIMBURSABLE",
                "value": "REIMBURSABLE"
              }
            ]
          }
        },
        {
          "columnName": "HOME_AGENCY",
          "type": "NONE",
          "expression": {
            "expressionStatement": "${HOME_AGENCY}",
            "alias": [
              {
                "name": "HOME_AGENCY",
                "value": "HOME_AGENCY"
              }
            ]
          }
        },
        {
          "columnName": "HOST_AGENCY",
          "type": "NONE",
          "expression": {
            "expressionStatement": "${HOST_AGENCY}",
            "alias": [
              {
                "name": "HOST_AGENCY",
                "value": "HOST_AGENCY"
              }
            ]
          }
        },
        {
          "columnName": "COMMENTS",
          "type": "NONE",
          "expression": {
            "expressionStatement": "${COMMENTS}",
            "alias": [
              {
                "name": "COMMENTS",
                "value": "COMMENTS"
              }
            ]
          }
        },
        {
          "columnName": "ELEMENT_AGENCY_OR_SERVICE",
          "type": "NONE",
          "expression": {
            "expressionStatement": "${ELEMENT_AGENCY_OR_SERVICE}",
            "alias": [
              {
                "name": "ELEMENT_AGENCY_OR_SERVICE",
                "value": "ELEMENT_AGENCY_OR_SERVICE"
              }
            ]
          }
        }
      ]
    },
    "fullyType2Sources": false,
    "subtype": "MODEL_BASED"
  },
  "virtualDataset": false,
  "description": ""
}